caliscope/__init__.py
caliscope/__main__.py
caliscope/configurator.py
caliscope/controller.py
caliscope/export.py
caliscope/helper.py
caliscope/intrinsic_stream_manager.py
caliscope/logger.py
caliscope/motion_trial.py
caliscope/packets.py
caliscope/synchronized_stream_manager.py
caliscope/tracker.py
caliscope/workspace_guide.py
caliscope/calibration/charuco.py
caliscope/calibration/draw_charuco.py
caliscope/calibration/intrinsic_calibrator.py
caliscope/calibration/stereocalibrator.py
caliscope/calibration/capture_volume/capture_volume.py
caliscope/calibration/capture_volume/point_estimates.py
caliscope/calibration/capture_volume/quality_controller.py
caliscope/calibration/capture_volume/seaborn_summaries.py
caliscope/calibration/capture_volume/set_origin_functions.py
caliscope/calibration/capture_volume/helper_functions/get_point_estimates.py
caliscope/calibration/capture_volume/helper_functions/get_stereotriangulated_table.py
caliscope/cameras/camera_array.py
caliscope/cameras/camera_array_initializer.py
caliscope/cameras/synchronizer.py
caliscope/gui/charuco_widget.py
caliscope/gui/extrinsic_playback_widget.py
caliscope/gui/log_widget.py
caliscope/gui/main_widget.py
caliscope/gui/post_processing_widget.py
caliscope/gui/progress_dialog.py
caliscope/gui/synched_frames_display.py
caliscope/gui/workspace_widget.py
caliscope/gui/camera_management/camera_display_widget.py
caliscope/gui/camera_management/multiplayback_widget.py
caliscope/gui/camera_management/playback_widget.py
caliscope/gui/frame_emitters/frame_dictionary_emitter.py
caliscope/gui/frame_emitters/playback_frame_emitter.py
caliscope/gui/frame_emitters/tools.py
caliscope/gui/icons/box3d-center.svg
caliscope/gui/icons/pyxy_logo.svg
caliscope/gui/icons/rotate-camera-left.svg
caliscope/gui/icons/rotate-camera-right.svg
caliscope/gui/utils/spinbox_utils.py
caliscope/gui/vizualize/camera_mesh.py
caliscope/gui/vizualize/playback_triangulation_widget.py
caliscope-0.6.7.dist-info/METADATA
caliscope-0.6.7.dist-info/WHEEL
caliscope-0.6.7.dist-info/entry_points.txt
caliscope-0.6.7.dist-info/licenses/LICENSE
caliscope-0.6.7.dist-info/RECORD
