Metadata-Version: 2.4
Name: caliscope
Version: 0.6.7
Summary: GUI based multicamera calibration that integrates with 2D landmark tracking to triangulate 3D landmark positions
Project-URL: repository, https://github.com/mprib/caliscope
Author-email: Mac Prible <prible@gmail.com>
License: BSD-2-Clause
License-File: LICENSE
Requires-Python: <3.12,>=3.10
Requires-Dist: mediapipe==0.10.20
Requires-Dist: numba>=0.57.0
Requires-Dist: opencv-contrib-python>=4.8.0.74
Requires-Dist: pandas>=1.5.0
Requires-Dist: pyarrow>=15.0.0
Requires-Dist: pyopengl>=3.1.6
Requires-Dist: pyqtgraph>=0.13.2
Requires-Dist: pyside6>=6.5.2
Requires-Dist: rtoml>=0.9.0
Requires-Dist: scipy>=1.10.1
Provides-Extra: dev
Requires-Dist: ipykernel>=6.22.0; extra == 'dev'
Requires-Dist: mkdocs-git-revision-date-localized-plugin>=1.2.0; extra == 'dev'
Requires-Dist: mkdocs-material>=9.1.6; extra == 'dev'
Requires-Dist: openpyxl; extra == 'dev'
Requires-Dist: pre-commit; extra == 'dev'
Requires-Dist: pymdown-extensions<11.0,>=9.11; extra == 'dev'
Requires-Dist: pytest>=7.3.0; extra == 'dev'
Requires-Dist: pywinctl; extra == 'dev'
Requires-Dist: ruff>=0.6.5; extra == 'dev'
